pybwa_lite/__init__.py
pybwa_lite/align.py
pybwa_lite/cli.py
pybwa_lite/fmidx.py
pybwa_lite/index.py
pybwa_lite/samtools.py
pybwa_lite-0.1.3.dist-info/METADATA
pybwa_lite-0.1.3.dist-info/WHEEL
pybwa_lite-0.1.3.dist-info/top_level.txt
pybwa_lite-0.1.3.dist-info/RECORD
