Metadata-Version: 2.4
Name: pybwa-lite
Version: 0.1.3
Summary: A lightweight Python implementation of the Burrows–Wheeler Aligner (BWA) with FM-index and multithreaded alignment.
Home-page: https://github.com/soumyapriyagoswami/pybwa.git
Author: Soumyapriya Goswami
Author-email: Soumyapriya Goswami <soumyapriya.goswami.it2023@kgec.ac.in>
License: MIT
Project-URL: Homepage, https://github.com/soumyapriyagoswami/pybwa
Classifier: Programming Language :: Python :: 3
Classifier: License :: OSI Approved :: MIT License
Classifier: Operating System :: OS Independent
Requires-Python: >=3.8
Requires-Dist: numpy>=1.20
Requires-Dist: tqdm>=4.60
Requires-Dist: pysam>=0.22
